singular_wrap_text/__init__.py
singular_wrap_text/wraptext.py
singular_wrap_text-1.0.1.dist-info/LICENSE.txt
singular_wrap_text-1.0.1.dist-info/METADATA
singular_wrap_text-1.0.1.dist-info/WHEEL
singular_wrap_text-1.0.1.dist-info/top_level.txt
singular_wrap_text-1.0.1.dist-info/RECORD
