Metadata-Version: 2.1
Name: singular_wrap_text
Version: 1.0.1
Summary: A sample Python project
Home-page: https://github.com/CleberPereiraAnalista/WrapText.git
Author: Cleber Almeida Pereira
Author-email: Cleber Almeida Pereira <cleber.ap.ads@gmail.com>
Maintainer-email: Cleber Almeida Pereira <cleber.ap.ads@gmail.com>
License: MIT License
Project-URL: Código fonte, https://github.com/CleberPereiraAnalista/WrapText.git
Keywords: wrap,quebra-de-linha,quebra
Classifier: Development Status :: 5 - Production/Stable
Classifier: License :: OSI Approved :: MIT License
Classifier: Natural Language :: Portuguese (Brazilian)
Classifier: Programming Language :: Python :: 3.7
Classifier: Programming Language :: Python :: 3.8
Classifier: Programming Language :: Python :: 3.9
Classifier: Programming Language :: Python :: 3.10
Classifier: Programming Language :: Python :: 3.11
Classifier: Programming Language :: Python :: 3.12
Classifier: Programming Language :: Python :: 3.13
Classifier: Programming Language :: Python :: 3 :: Only
Requires-Python: >=3.7, <4
License-File: LICENSE.txt
